bulma/__init__.py
bulma/__main__.py
bulma/logger.py
bulma_load-0.0.8.dist-info/LICENSE
bulma_load-0.0.8.dist-info/METADATA
bulma_load-0.0.8.dist-info/WHEEL
bulma_load-0.0.8.dist-info/top_level.txt
bulma_load-0.0.8.dist-info/RECORD
