Metadata-Version: 2.1
Name: bulma-load
Version: 0.0.8
Summary: Wrapper for Vegeta Load Testing tool
Home-page: https://github.com/kiran94/bulma
Author: Kiran Patel
Author-email: na@gmail.com
License: MIT
Keywords: vegeta load testing stress
Platform: UNKNOWN
Classifier: Programming Language :: Python :: 3
Classifier: License :: OSI Approved :: MIT License
Classifier: Operating System :: OS Independent
Requires-Python: >=3.6
Requires-Dist: pandas
Requires-Dist: tabulate
Requires-Dist: rich
